data_preparation/BIO_tag_generator.py
data_preparation/__init__.py
data_preparation/gather_corpus_stats.py
data_preparation/preprocess_BIO_tags.py
data_preparation/seq2seq_data_generator.py
data_preparation/heideltime/__init__.py
data_preparation/heideltime/heideltime_generate_tempeval_data.py
data_preparation/heideltime/subset_heideltime_data.py
temporal_taggers/__init__.py
temporal_taggers/evaluation/__init__.py
temporal_taggers/evaluation/seq2seq_evaluation.py
temporal_taggers/evaluation/tagger_evaluation.py
temporal_taggers/evaluation/tempeval3_toolkit-master/TE3-evaluation.py
temporal_taggers/evaluation/tempeval3_toolkit-master/__init__.py
temporal_taggers/evaluation/tempeval3_toolkit-master/evaluation-entities/__init__.py
temporal_taggers/evaluation/tempeval3_toolkit-master/evaluation-entities/evaluate_entities.py
temporal_taggers/evaluation/tempeval3_toolkit-master/evaluation-relations/__init__.py
temporal_taggers/evaluation/tempeval3_toolkit-master/evaluation-relations/relation_to_timegraph.py
temporal_taggers/evaluation/tempeval3_toolkit-master/evaluation-relations/temporal_evaluation.py
temporal_taggers/seq2seq/__init__.py
temporal_taggers/seq2seq/utils.py
temporal_taggers/tagger/BERTWithCRF.py
temporal_taggers/tagger/BERTWithDateLayerTokenClassification.py
temporal_taggers/tagger/DateTokenizer.py
temporal_taggers/tagger/__init__.py
temporal_taggers/tagger/ner_tasks.py
temporal_taggers/tagger/ner_tasks_crf.py
temporal_taggers/tagger/ner_tasks_date_extra_layer.py
temporal_taggers/tagger/utils.py
temporal_taggers-0.0.1.dist-info/METADATA
temporal_taggers-0.0.1.dist-info/WHEEL
temporal_taggers-0.0.1.dist-info/top_level.txt
temporal_taggers-0.0.1.dist-info/RECORD
