Metadata-Version: 2.1
Name: temporal-taggers
Version: 0.0.1
Summary: Neural temporal taggers with Transformer architectures
Home-page: https://github.com/satya77/Transformer_Temporal_Tagger
Author: Satya Almasian and Dennis Aumiller
Author-email: almasian@informatik.uni-heidelberg.de
License: UNKNOWN
Platform: UNKNOWN
Classifier: Programming Language :: Python :: 3
Classifier: Programming Language :: Python :: 3.7
Requires-Dist: transformers (>=4.3.3)
Requires-Dist: torch (>=1.8)
Requires-Dist: datasets
Requires-Dist: spacy (>=3.0)
Requires-Dist: beautifulsoup4 (>=4.9)
Requires-Dist: seqeval
Requires-Dist: conllu
Requires-Dist: filelock
